{
  "DT": {
    "HP_LOAD_MAP":        1610612736,
    "HP_DLD_FLAGS":       1610612737,
    "HP_DLD_HOOK":        1610612738,
    "HP_UX10_INIT":       1610612739,
    "HP_UX10_INITSZ":     1610612740,
    "HP_PREINIT":         1610612741,
    "HP_PREINITSZ":       1610612742,
    "HP_NEEDED":          1610612743,
    "HP_TIME_STAMP":      1610612744,
    "HP_CHECKSUM":        1610612745,
    "HP_GST_SIZE":        1610612746,
    "HP_GST_VERSION":     1610612747,
    "HP_GST_HASHVAL":     1610612748,
    "HP_EPLTREL":         1610612749,
    "HP_EPLTRELSZ":       1610612750,
    "HP_FILTERED":        1610612751,
    "HP_FILTER_TLS":      1610612752,
    "HP_COMPAT_FILTERED": 1610612753,
    "HP_LAZYLOAD":        1610612754,
    "HP_BIND_NOW_COUNT":  1610612755,
    "PLT":                1610612756,
    "PLT_SIZE":           1610612757,
    "DLT":                1610612758,
    "DLT_SIZE":           1610612759,
    "HP_DEBUG_PRIVATE": 1,
    "HP_DEBUG_CALLBACK": 2,
    "HP_DEBUG_CALLBACK_BOR": 4,
    "HP_NO_ENVVAR": 8,
    "HP_BIND_NOW": 16,
    "HP_BIND_NONFATAL": 32,
    "HP_BIND_VERBOSE": 64,
    "HP_BIND_RESTRICTED": 128,
    "HP_BIND_SYMBOLIC": 256,
    "HP_RPATH_FIRST": 512,
    "HP_BIND_DEPTH_FIRST": 1024,
    "HP_GST": 2048,
    "HP_SHLIB_FIXED": 4096,
    "HP_MERGE_SHLIB_SEG": 8192,
    "HP_NODELETE": 16384,
    "HP_GROUP": 32768,
    "HP_PROTECT_LINKAGE_TABLE": 65536
  },
  "SHT": {
    "PARISC_EXT": 1879048192,
    "PARISC_UNWIND": 1879048193,
    "PARISC_DOC": 1879048194,
    "PARISC_ANNOT": 1879048195,
    "PARISC_DLKM": 1879048196,
    "HP_OVLBITS": 1610612736,
    "HP_DLKM": 1610612736,
    "HP_COMDAT": 1610612736,
    "HP_OBJDICT": 1610612736,
    "HP_ANNOT": 1610612736
  },
  "PT": {
    "PARISC_ARCHEXT": 1879048192,
    "PARISC_UNWIND": 1879048193,
    "PARISC_WEAKORDER": 1879048194,
    "HP_TLS": 1610612736,
    "HP_CORE_NONE": 1610612736,
    "HP_CORE_VERSION": 1610612736,
    "HP_CORE_KERNEL": 1610612736,
    "HP_CORE_COMM": 1610612736,
    "HP_CORE_PROC": 1610612736,
    "HP_CORE_LOADABLE": 1610612736,
    "HP_CORE_STACK": 1610612736,
    "HP_CORE_SHM": 1610612736,
    "HP_CORE_MMF": 1610612736,
    "HP_PARALLEL": 1610612736,
    "HP_FASTBIND": 1610612736,
    "HP_OPT_ANNOT": 1610612736,
    "HP_HSL_ANNOT": 1610612736,
    "HP_STACK": 1610612736,
    "HP_CORE_UTSNAME": 1610612736
  },
  "NT": {
    "HP_COMPILER": 1,
    "HP_COPYRIGHT": 2,
    "HP_VERSION": 3,
    "HP_SRCFILE_INFO": 4,
    "HP_LINKER": 5,
    "HP_INSTRUMENTED": 6,
    "HP_UX_OPTIONS": 7
  },
  "structs": {}
}
